COPYING.txt
README.rst
contrib/PKGBUILD
contrib/cram.vim
docs/conf.py
docs/contributors.rst
docs/development.rst
docs/getting_started.rst
docs/index.rst
docs/news.rst
docs/prysk_news.rst
docs/pytest-plugin.rst
docs/readme.rst
examples/.hidden.t
examples/bare.t
examples/empty.t
examples/env.t
examples/fail.t
examples/missingeol.t
examples/skip.t
examples/test.t
frysk/__init__.py
frysk/__main__.py
frysk/cli.py
frysk/diff.py
frysk/process.py
frysk/settings.py
frysk/test.py
frysk/xunit.py
noxfile.py
poetry.lock
pyproject.toml
scripts/md5.py
frysk-0.2.0.dist-info/COPYING.txt
frysk-0.2.0.dist-info/METADATA
frysk-0.2.0.dist-info/WHEEL
frysk-0.2.0.dist-info/entry_points.txt
frysk-0.2.0.dist-info/RECORD
